leanup/__init__.py
leanup/const.py
leanup/cli/__init__.py
leanup/cli/repo.py
leanup/repo/__init__.py
leanup/repo/elan.py
leanup/repo/manager.py
leanup/utils/__init__.py
leanup/utils/basic.py
leanup/utils/config.py
leanup/utils/custom_logger.py
leanup-0.1.9.dist-info/licenses/LICENSE
tests/__init__.py
tests/conftest.py
tests/test_cli.py
tests/test_config.py
tests/test_elan_manager.py
tests/test_lean_repo.py
tests/test_utils.py
leanup-0.1.9.dist-info/METADATA
leanup-0.1.9.dist-info/WHEEL
leanup-0.1.9.dist-info/entry_points.txt
leanup-0.1.9.dist-info/top_level.txt
leanup-0.1.9.dist-info/RECORD
