Metadata-Version: 2.4
Name: leanup
Version: 0.1.9
Summary: Python package for Lean Environment Management
Author: Lean-zh Community
Author-email: leanprover@outlook.com
Maintainer: Lean-zh Community
Maintainer-email: leanprover@outlook.com
License: MIT license
Requires-Python: >=3.6
License-File: LICENSE
Requires-Dist: gitpython
Requires-Dist: psutil
Requires-Dist: toml
Requires-Dist: click
Requires-Dist: platformdirs
Requires-Dist: loguru
Requires-Dist: requests
Requires-Dist: colorama
Provides-Extra: dev
Requires-Dist: coverage; extra == "dev"
Requires-Dist: mypy; extra == "dev"
Requires-Dist: pytest; extra == "dev"
Requires-Dist: ruff; extra == "dev"
Requires-Dist: mkdocs>=1.4.0; extra == "dev"
Requires-Dist: mkdocs-material>=9.0.0; extra == "dev"
Requires-Dist: mkdocs-static-i18n>=0.5.0; extra == "dev"
Requires-Dist: pytest>=7.0.0; extra == "dev"
Requires-Dist: pytest-cov>=4.0.0; extra == "dev"
Dynamic: license-file
